toggldash/__init__.py
toggldash/app/__init__.py
toggldash/app/toggldash.py
toggldash/response/__init__.py
toggldash/response/get_response.py
toggldash/response/process_response.py
toggldash-1.0.6.dist-info/LICENSE
toggldash-1.0.6.dist-info/METADATA
toggldash-1.0.6.dist-info/WHEEL
toggldash-1.0.6.dist-info/entry_points.txt
toggldash-1.0.6.dist-info/top_level.txt
toggldash-1.0.6.dist-info/RECORD
