Metadata-Version: 2.1
Name: toggldash
Version: 1.0.6
Summary: plots data from toggl track
Home-page: https://github.com/atharva-2001/Toggl-Dashboard
Author: Atharva Arya
Author-email: aryaatharva18@gmail.com
License: MIT
Platform: UNKNOWN
Classifier: License :: OSI Approved :: MIT License
Classifier: Programming Language :: Python :: 3
Classifier: Operating System :: OS Independent
Requires-Python: >=3.7
Requires-Dist: dash
Requires-Dist: plotly
Requires-Dist: pandas
Requires-Dist: numpy
Requires-Dist: requests
